[
    {
      "id": 1,
      "image": "https://i.ibb.co/sgrmsDy/Junior-Lambs.webp",
      "title": "Toddler Childcare",
      "age": "3-5 Years3-5 Years",
      "link": "https://example.com/link1",
      "description": "Kidzo mission is to provide affordable high-quality early education and childcare",
      "bg_color": "#F1E7DE"
    },
    {
      "id": 2,
      "image": "https://i.ibb.co/yfp1hbR/Pre-School.webp",
      "title": "Kindergarten",
      "age": "2-9 yrs2-9 yrs",
      "link": "https://example.com/link2",
      "description": "He nicked it starkers lost the plot argy-bargy pear shaped faff about give us a",
      "bg_color": "#b6e3df"
    },
    {
      "id": 3,
      "image": "https://i.ibb.co/syfyVVc/Kindergarten.webp",
      "title": "Pre School",
      "age": "5-8 yrs5-8 yrs",
      "link": "https://example.com/link3",
      "description": "He nicked it starkers lost the plot argy-bargy pear shaped faff about give us a",
      "bg_color": "#fde1a4"
    },
    {
      "id": 4,
      "image": "https://i.ibb.co/6NXMvRh/Toddler-Childcare.webp",
      "title": "Junior Lambs",
      "age": "12-14 yrs12-14 yrs",
      "link": "https://example.com/link4",
      "description": "He nicked it starkers lost the plot argy-bargy pear shaped faff about give us a",
      "bg_color": "#f5ccc1"
    }
  ]